xnlp/__init__.py
xnlp/parser/__init__.py
xnlp/parser/combinator.py
xnlp/parser/monad.py
xnlp/parser/util.py
x_nlp-0.1.6.dist-info/LICENSE
x_nlp-0.1.6.dist-info/METADATA
x_nlp-0.1.6.dist-info/WHEEL
x_nlp-0.1.6.dist-info/top_level.txt
x_nlp-0.1.6.dist-info/RECORD
