Metadata-Version: 2.1
Name: x-nlp
Version: 0.1.6
Summary: Library of helper functions for Natural Language Processing related algorithms (designed for the TechX NLP course).
Home-page: https://github.com/techx-nlp/x-nlp
Author: David Ma
Author-email: davidma@davidma.cn
License: MIT
Platform: UNKNOWN
